allennlp_runmodel/__init__.py
allennlp_runmodel/__main__.py
allennlp_runmodel/_version.py
allennlp_runmodel/globvars.py
allennlp_runmodel/version.py
allennlp_runmodel/webservice.py
allennlp_runmodel/commands/__init__.py
allennlp_runmodel/commands/run.py
allennlp_runmodel-0.2.1.dist-info/AUTHORS.md
allennlp_runmodel-0.2.1.dist-info/METADATA
allennlp_runmodel-0.2.1.dist-info/WHEEL
allennlp_runmodel-0.2.1.dist-info/entry_points.txt
allennlp_runmodel-0.2.1.dist-info/namespace_packages.txt
allennlp_runmodel-0.2.1.dist-info/top_level.txt
allennlp_runmodel-0.2.1.dist-info/RECORD
