Metadata-Version: 2.1
Name: allennlp-runmodel
Version: 0.2.1
Summary: Run a AllenNLP trained model, and serve it with WebAPI.
Home-page: https://github.com/tanbro/allennlp-runmodel
Author: liu xue yan
Author-email: liu_xue_yan@foxmail.com
License: UNKNOWN
Platform: UNKNOWN
Requires-Dist: allennlp
Requires-Dist: aiohttp
Requires-Dist: click
Provides-Extra: toml
Requires-Dist: toml ; extra == 'toml'
Provides-Extra: yaml
Requires-Dist: PyYAML ; extra == 'yaml'
